fastentrypoints.py
fprime_gds/__init__.py
fprime_gds/version.py
fprime_gds/common/__init__.py
fprime_gds/common/handlers.py
fprime_gds/common/transport.py
fprime_gds/common/zmq_transport.py
fprime_gds/common/communication/__init__.py
fprime_gds/common/communication/checksum.py
fprime_gds/common/communication/framing.py
fprime_gds/common/communication/ground.py
fprime_gds/common/communication/updown.py
fprime_gds/common/communication/adapters/__init__.py
fprime_gds/common/communication/adapters/base.py
fprime_gds/common/communication/adapters/ip.py
fprime_gds/common/communication/adapters/uart.py
fprime_gds/common/communication/ccsds/__init__.py
fprime_gds/common/communication/ccsds/apid.py
fprime_gds/common/communication/ccsds/chain.py
fprime_gds/common/communication/ccsds/space_data_link.py
fprime_gds/common/communication/ccsds/space_packet.py
fprime_gds/common/controllers/__init__.py
fprime_gds/common/data_types/__init__.py
fprime_gds/common/data_types/ch_data.py
fprime_gds/common/data_types/cmd_data.py
fprime_gds/common/data_types/event_data.py
fprime_gds/common/data_types/exceptions.py
fprime_gds/common/data_types/file_data.py
fprime_gds/common/data_types/pkt_data.py
fprime_gds/common/data_types/sys_data.py
fprime_gds/common/decoders/__init__.py
fprime_gds/common/decoders/ch_decoder.py
fprime_gds/common/decoders/decoder.py
fprime_gds/common/decoders/event_decoder.py
fprime_gds/common/decoders/file_decoder.py
fprime_gds/common/decoders/pkt_decoder.py
fprime_gds/common/distributor/__init__.py
fprime_gds/common/distributor/distributor.py
fprime_gds/common/encoders/__init__.py
fprime_gds/common/encoders/ch_encoder.py
fprime_gds/common/encoders/cmd_encoder.py
fprime_gds/common/encoders/encoder.py
fprime_gds/common/encoders/event_encoder.py
fprime_gds/common/encoders/file_encoder.py
fprime_gds/common/encoders/pkt_encoder.py
fprime_gds/common/encoders/seq_writer.py
fprime_gds/common/files/File Decoder Documentation.txt
fprime_gds/common/files/__init__.py
fprime_gds-4.0.1.dist-info/licenses/LICENSE.txt
fprime_gds-4.0.1.dist-info/licenses/NOTICE.txt
fprime_gds-4.0.1.dist-info/METADATA
fprime_gds-4.0.1.dist-info/WHEEL
fprime_gds-4.0.1.dist-info/entry_points.txt
fprime_gds-4.0.1.dist-info/top_level.txt
fprime_gds-4.0.1.dist-info/RECORD
