Metadata-Version: 2.4
Name: fprime-gds
Version: 4.0.1
Summary: F Prime Flight Software Ground Data System layer
Author-email: Michael Starch <Michael.D.Starch@jpl.nasa.gov>, Thomas Boyer-Chammard <Thomas.Boyer.Chammard@jpl.nasa.gov>
License: 
Project-URL: Homepage, https://fprime.jpl.nasa.gov
Project-URL: Documentation, https://nasa.github.io/fprime/
Project-URL: Repository, https://github.com/fprime-community/fprime-gds
Keywords: fprime,embedded,nasa,flight,software
Classifier: Development Status :: 5 - Production/Stable
Classifier: Intended Audience :: Developers
Classifier: Operating System :: Unix
Classifier: Operating System :: POSIX
Classifier: Programming Language :: Python
Classifier: Programming Language :: Python :: 3
Classifier: Programming Language :: Python :: 3.9
Classifier: Programming Language :: Python :: 3.10
Classifier: Programming Language :: Python :: 3.11
Classifier: Programming Language :: Python :: 3.12
Classifier: Programming Language :: Python :: 3.13
Classifier: Programming Language :: Python :: Implementation :: CPython
Classifier: Programming Language :: Python :: Implementation :: PyPy
Classifier: License :: OSI Approved :: Apache Software License
Requires-Python: >=3.9
License-File: LICENSE.txt
License-File: NOTICE.txt
Requires-Dist: flask>=3.0.0
Requires-Dist: flask_compress>=1.11
Requires-Dist: pyzmq>=24.0.1
Requires-Dist: pexpect>=4.8.0
Requires-Dist: pytest>=6.2.4
Requires-Dist: flask_restful>=0.3.8
Requires-Dist: fprime-tools>=3.4.3
Requires-Dist: argcomplete>=1.12.3
Requires-Dist: Jinja2>=2.11.3
Requires-Dist: openpyxl>=3.0.10
Requires-Dist: pyserial>=3.5
Requires-Dist: pydantic>=2.6
Requires-Dist: lark>=1.2.2
Requires-Dist: PyYAML>=6.0.2
Requires-Dist: spacepackets>=0.30.0
Requires-Dist: crc>=7.0.0
Dynamic: license-file
